sch/__init__.py
sch/cli.py
sch/sch.py
tests/__init__.py
tests/test_sch.py
sch-0.7.2.dist-info/LICENSE
sch-0.7.2.dist-info/METADATA
sch-0.7.2.dist-info/WHEEL
sch-0.7.2.dist-info/entry_points.txt
sch-0.7.2.dist-info/top_level.txt
sch-0.7.2.dist-info/RECORD
