Metadata-Version: 2.1
Name: sch
Version: 0.7.2
Summary: A cron shell wrapper for registering and updating cron jobs automatically in healthchecks
Home-page: https://gitlab.science.ru.nl/bram/sch
Author: Bram Daams
Author-email: b.daams@science.ru.nl
License: GNU General Public License v3
Keywords: sch
Platform: UNKNOWN
Classifier: Development Status :: 2 - Pre-Alpha
Classifier: Intended Audience :: Developers
Classifier: License :: OSI Approved :: GNU General Public License v3 (GPLv3)
Classifier: Natural Language :: English
Classifier: Topic :: System :: Monitoring
Classifier: Programming Language :: Python :: 3
Classifier: Programming Language :: Python :: 3.5
Classifier: Programming Language :: Python :: 3.6
Classifier: Programming Language :: Python :: 3.7
Classifier: Programming Language :: Python :: 3.8
Requires-Python: >=3.5
Requires-Dist: arrow
Requires-Dist: click (>=7.0)
Requires-Dist: configparser
Requires-Dist: python-crontab
Requires-Dist: requests
Requires-Dist: tzlocal
